Metadata-Version: 2.1
Name: eggtart
Version: 0.0.10
Summary: eggtart is a Data Analysis package
Author: Dr Anna Sung and Prof Kelvin Leong
Author-email: <k.leong@chester.ac.uk>
Keywords: python,first package
Classifier: Development Status :: 3 - Alpha
Classifier: Intended Audience :: Science/Research
Classifier: Intended Audience :: Education
Classifier: Intended Audience :: Other Audience
Classifier: Programming Language :: Python :: 2
Classifier: Programming Language :: Python :: 3
Classifier: Operating System :: MacOS :: MacOS X
Classifier: Operating System :: Microsoft :: Windows
License-File: LICENSE.txt
Requires-Dist: pandas
Requires-Dist: transformers
Requires-Dist: tabulate
